{"trial_id": "0141", "hyperparameters": {"space": [{"class_name": "Int", "config": {"name": "units1", "default": null, "conditions": [], "min_value": 32, "max_value": 512, "step": 32, "sampling": "linear"}}, {"class_name": "Float", "config": {"name": "dropout1", "default": 0.0, "conditions": [], "min_value": 0.0, "max_value": 0.5, "step": 0.1, "sampling": "linear"}}, {"class_name": "Int", "config": {"name": "units2", "default": null, "conditions": [], "min_value": 32, "max_value": 512, "step": 32, "sampling": "linear"}}, {"class_name": "Float", "config": {"name": "dropout2", "default": 0.0, "conditions": [], "min_value": 0.0, "max_value": 0.5, "step": 0.1, "sampling": "linear"}}, {"class_name": "Int", "config": {"name": "units3", "default": null, "conditions": [], "min_value": 32, "max_value": 512, "step": 32, "sampling": "linear"}}, {"class_name": "Float", "config": {"name": "dropout3", "default": 0.0, "conditions": [], "min_value": 0.0, "max_value": 0.5, "step": 0.1, "sampling": "linear"}}, {"class_name": "Choice", "config": {"name": "learning_rate", "default": 0.01, "conditions": [], "values": [0.01, 0.001, 0.0001], "ordered": true}}], "values": {"units1": 128, "dropout1": 0.30000000000000004, "units2": 384, "dropout2": 0.2, "units3": 224, "dropout3": 0.1, "learning_rate": 0.001, "tuner/epochs": 50, "tuner/initial_epoch": 17, "tuner/bracket": 3, "tuner/round": 3, "tuner/trial_id": "0137"}}, "metrics": {"metrics": {"accuracy": {"direction": "max", "observations": [{"value": [0.7406504154205322], "step": 8}]}, "loss": {"direction": "min", "observations": [{"value": [0.5199111700057983], "step": 8}]}, "val_accuracy": {"direction": "max", "observations": [{"value": [0.7329268455505371], "step": 8}]}, "val_loss": {"direction": "min", "observations": [{"value": [0.5254748463630676], "step": 8}]}}}, "score": 0.7329268455505371, "best_step": 8, "status": "COMPLETED", "message": null}